sqldrafter/__init__.py
sqldrafter/analysisField.py
sqldrafter/analysisJoinInfo.py
sqldrafter/analysisPartion.py
sqldrafter/analysisUniq.py
sqldrafter/cli.py
sqldrafter/generate_schema.py
sqldrafter/space_manager.py
sqldrafter/util.py
sqlDrafter-0.0.8.dist-info/METADATA
sqlDrafter-0.0.8.dist-info/WHEEL
sqlDrafter-0.0.8.dist-info/entry_points.txt
sqlDrafter-0.0.8.dist-info/top_level.txt
sqlDrafter-0.0.8.dist-info/RECORD
